spotify_internal/__init__.py
spotify_internal/endpoints.py
spotify_internal/internal.py
spotify_internal/login.py
spotify_internal/utils.py
spotify_internal-0.1.9.dist-info/LICENSE.txt
spotify_internal-0.1.9.dist-info/METADATA
spotify_internal-0.1.9.dist-info/WHEEL
spotify_internal-0.1.9.dist-info/RECORD
